script_magic/__init__.py
script_magic/ai_integration.py
script_magic/code.py
script_magic/create.py
script_magic/delete.py
script_magic/edit.py
script_magic/github_gist_finder.py
script_magic/github_integration.py
script_magic/list.py
script_magic/logger.py
script_magic/mapping_manager.py
script_magic/mapping_setup.py
script_magic/model_providers.py
script_magic/pep723.py
script_magic/rich_output.py
script_magic/run.py
script_magic-1.10.0.dist-info/METADATA
script_magic-1.10.0.dist-info/WHEEL
script_magic-1.10.0.dist-info/entry_points.txt
script_magic-1.10.0.dist-info/licenses/LICENSE
script_magic-1.10.0.dist-info/RECORD
