Metadata-Version: 2.4
Name: script-magic
Version: 1.10.0
Summary: Command-line script utility toolkit that simplifies common scripting tasks with AI-powered script generation, GitHub Gist integration for cross-device synchronization, and automatic dependency management. Create, run, and manage scripts with natural language prompts.
Project-URL: Homepage, https://github.com/ThomasRohde/script-magic
Project-URL: Bug Tracker, https://github.com/ThomasRohde/script-magic/issues
Project-URL: Documentation, https://github.com/ThomasRohde/script-magic#readme
Project-URL: Source Code, https://github.com/ThomasRohde/script-magic
Author-email: Thomas Klok Rohde <rohde.thomas@gmail.com>
License: MIT
License-File: LICENSE
Classifier: Development Status :: 4 - Beta
Classifier: Intended Audience :: Developers
Classifier: License :: OSI Approved :: MIT License
Classifier: Operating System :: OS Independent
Classifier: Programming Language :: Python :: 3
Classifier: Programming Language :: Python :: 3.12
Classifier: Topic :: Software Development :: Libraries :: Python Modules
Requires-Python: >=3.12
Requires-Dist: anthropic>=0.49.0
Requires-Dist: click>=8.1.8
Requires-Dist: google-generativeai>=0.8.4
Requires-Dist: instructor>=1.7.2
Requires-Dist: openai>=1.65.1
Requires-Dist: pip-system-certs>=4.0
Requires-Dist: pygithub>=2.6.1
Requires-Dist: rich>=13.9.4
Requires-Dist: tabulate>=0.9.0
Requires-Dist: textual[syntax]>=2.1.2
